examples/__init__.py
examples/example_conductor.py
examples/example_oss.py
examples/example_server.py
examples/example_utils.py
vines_worker_sdk/__init__.py
vines_worker_sdk/conductor/__init__.py
vines_worker_sdk/conductor/typing.py
vines_worker_sdk/conductor/worker.py
vines_worker_sdk/exceptions/__init__.py
vines_worker_sdk/logger/__init__.py
vines_worker_sdk/oss/__init__.py
vines_worker_sdk/server/__init__.py
vines_worker_sdk/server/exceptions.py
vines_worker_sdk/utils/__init__.py
vines_worker_sdk/utils/files.py
vines_worker_sdk/utils/string.py
vines_worker_sdk-0.0.21.dist-info/METADATA
vines_worker_sdk-0.0.21.dist-info/WHEEL
vines_worker_sdk-0.0.21.dist-info/top_level.txt
vines_worker_sdk-0.0.21.dist-info/RECORD
